README.md
setup.py
pyjsondb/__init__.py
pyjsondb/db.py
pyjsondb/table.py
pyjsondb.egg-info/PKG-INFO
pyjsondb.egg-info/SOURCES.txt
pyjsondb.egg-info/dependency_links.txt
pyjsondb.egg-info/top_level.txt