Metadata-Version: 2.1
Name: pyjsondb
Version: 0.0.1
Summary: A small satabase package
Home-page: https://github.com/pranavbaburaj/pyjdondb
Author: Pranav Baburaj
License: UNKNOWN
Platform: UNKNOWN
Classifier: Programming Language :: Python :: 3
Classifier: License :: OSI Approved :: MIT License
Classifier: Operating System :: OS Independent
Requires-Python: >=3.6
